core/__init__.py
core/model.py
core/other.py
core/policy.py
core/q.py
core/tf_base.py
core/torch_base.py
core/torch_base_old.py
explore/__init__.py
explore/policy_based.py
explore/value_based.py
logger/__init__.py
logger/wandb.py
objective/__init__.py
objective/base.py
objective/policy_gradient.py
objective/td_learning.py
recorder/__init__.py
recorder/recorders.py
recorder/transition.py
replay/__init__.py
replay/buffers.py
wrapper/__init__.py
wrapper/monitor.py
foam_rl-0.0.1.dist-info/LICENSE
foam_rl-0.0.1.dist-info/METADATA
foam_rl-0.0.1.dist-info/WHEEL
foam_rl-0.0.1.dist-info/top_level.txt
foam_rl-0.0.1.dist-info/RECORD
