Metadata-Version: 2.1
Name: foam-rl
Version: 0.0.1
Summary: Framework Agnostic Modular Reinforcement Learning Library
Home-page: https://github.com/ajagekarakshay/foam
Author: Akshay Ajagekar
Author-email: me@akshayajagekar.com
License: UNKNOWN
Project-URL: Bug Tracker, https://www.akshayajagekar.com
Platform: UNKNOWN
Classifier: Programming Language :: Python :: 3
Classifier: License :: OSI Approved :: MIT License
Classifier: Operating System :: OS Independent
Requires-Python: >=3.6
License-File: LICENSE
